accelbyte_py_sdk/api/matchmaking/__init__.py
accelbyte_py_sdk/api/matchmaking/errors.py
accelbyte_py_sdk/api/matchmaking/models/__init__.py
accelbyte_py_sdk/api/matchmaking/models/log_app_message_declaration.py
accelbyte_py_sdk/api/matchmaking/models/models_alliance_flexing_rule.py
accelbyte_py_sdk/api/matchmaking/models/models_alliance_rule.py
accelbyte_py_sdk/api/matchmaking/models/models_alliance_rule_v1.py
accelbyte_py_sdk/api/matchmaking/models/models_bucket_mmr_rule.py
accelbyte_py_sdk/api/matchmaking/models/models_channel.py
accelbyte_py_sdk/api/matchmaking/models/models_channel_request.py
accelbyte_py_sdk/api/matchmaking/models/models_channel_v1.py
accelbyte_py_sdk/api/matchmaking/models/models_combination.py
accelbyte_py_sdk/api/matchmaking/models/models_create_channel_response.py
accelbyte_py_sdk/api/matchmaking/models/models_create_mock_ticket.py
accelbyte_py_sdk/api/matchmaking/models/models_dequeue_request.py
accelbyte_py_sdk/api/matchmaking/models/models_flexing_rule.py
accelbyte_py_sdk/api/matchmaking/models/models_get_channels_response.py
accelbyte_py_sdk/api/matchmaking/models/models_get_mock_matches_response.py
accelbyte_py_sdk/api/matchmaking/models/models_get_mock_tickets_response.py
accelbyte_py_sdk/api/matchmaking/models/models_import_config_response.py
accelbyte_py_sdk/api/matchmaking/models/models_match_add_user_into_session_request.py
accelbyte_py_sdk/api/matchmaking/models/models_match_option.py
accelbyte_py_sdk/api/matchmaking/models/models_match_option_rule.py
accelbyte_py_sdk/api/matchmaking/models/models_match_result_request.py
accelbyte_py_sdk/api/matchmaking/models/models_match_result_response.py
accelbyte_py_sdk/api/matchmaking/models/models_matching_ally.py
accelbyte_py_sdk/api/matchmaking/models/models_matching_party.py
accelbyte_py_sdk/api/matchmaking/models/models_matching_rule.py
accelbyte_py_sdk/api/matchmaking/models/models_matchmaking_result.py
accelbyte_py_sdk/api/matchmaking/models/models_mock_match.py
accelbyte_py_sdk_service_matchmaking-0.20.0.dist-info/METADATA
accelbyte_py_sdk_service_matchmaking-0.20.0.dist-info/WHEEL
accelbyte_py_sdk_service_matchmaking-0.20.0.dist-info/top_level.txt
accelbyte_py_sdk_service_matchmaking-0.20.0.dist-info/RECORD
