Metadata-Version: 2.4
Name: accelbyte-py-sdk-service-matchmaking
Version: 0.20.0
Summary: AccelByte Python SDK - AccelByte Gaming Services Matchmaking Service
Requires-Python: >=3.9
Requires-Dist: accelbyte-py-sdk-core
